[{
        "stargazers_count": 48579,
        "forks_count": 12147,
        "contributors": {
            "login": [
                "josephmisiti",
                "josephmmisiti",
                "hslatman",
                "0asa",
                "ajkl",
                "ipcenas",
                "cogmission",
                "spekulatius",
                "basickarl",
                "NathanEpstein"
            ],
            "url": [
                "https://api.github.com/users/josephmisiti",
                "https://api.github.com/users/josephmmisiti",
                "https://api.github.com/users/hslatman",
                "https://api.github.com/users/0asa",
                "https://api.github.com/users/ajkl",
                "https://api.github.com/users/ipcenas",
                "https://api.github.com/users/cogmission",
                "https://api.github.com/users/spekulatius",
                "https://api.github.com/users/basickarl",
                "https://api.github.com/users/NathanEpstein"
            ],
            "contributions": [
                671,
                105,
                21,
                12,
                11,
                9,
                8,
                7,
                7,
                7
            ]
        }
    },
    {
        "stargazers_count": 4009,
        "forks_count": 2878,
        "contributors": {
            "login": [
                "wepe",
                "junlulocky",
                "CorcovadoMing",
                "enjoyhot",
                "poyuwu"
            ],
            "url": [
                "https://api.github.com/users/wepe",
                "https://api.github.com/users/junlulocky",
                "https://api.github.com/users/CorcovadoMing",
                "https://api.github.com/users/enjoyhot",
                "https://api.github.com/users/poyuwu"
            ],
            "contributions": [
                66,
                3,
                1,
                1,
                1
            ]
        }
    },
    {
        "stargazers_count": 3448,
        "forks_count": 6201,
        "contributors": {
            "login": [
                "jared-weed",
                "adarsh0806",
                "nickyfoto",
                "napratin",
                "jxm-math",
                "fixingitnow",
                "clapollo",
                "jaredweed1990",
                "kevdonk",
                "brandon-o"
            ],
            "url": [
                "https://api.github.com/users/jared-weed",
                "https://api.github.com/users/adarsh0806",
                "https://api.github.com/users/nickyfoto",
                "https://api.github.com/users/napratin",
                "https://api.github.com/users/jxm-math",
                "https://api.github.com/users/fixingitnow",
                "https://api.github.com/users/clapollo",
                "https://api.github.com/users/jaredweed1990",
                "https://api.github.com/users/kevdonk",
                "https://api.github.com/users/brandon-o"
            ],
            "contributions": [
                165,
                94,
                29,
                25,
                9,
                4,
                2,
                2,
                2,
                1
            ]
        }
    },
    {
        "stargazers_count": 3781,
        "forks_count": 3461,
        "contributors": {
            "login": [
                "Jack-Cherish",
                "jiangf13",
                "eecn",
                "Cugtyt",
                "YoungMStudio"
            ],
            "url": [
                "https://api.github.com/users/Jack-Cherish",
                "https://api.github.com/users/jiangf13",
                "https://api.github.com/users/eecn",
                "https://api.github.com/users/Cugtyt",
                "https://api.github.com/users/YoungMStudio"
            ],
            "contributions": [
                162,
                6,
                2,
                1,
                1
            ]
        }
    },
    {
        "stargazers_count": 24773,
        "forks_count": 5812,
        "contributors": {
            "login": [
                "ZuzooVn",
                "lsvih",
                "Pirikara",
                "tuanphuc",
                "SusieXu",
                "dangsonbk",
                "acastrounis",
                "benedekrozemberczki",
                "giuliatondin",
                "jwasham"
            ],
            "url": [
                "https://api.github.com/users/ZuzooVn",
                "https://api.github.com/users/lsvih",
                "https://api.github.com/users/Pirikara",
                "https://api.github.com/users/tuanphuc",
                "https://api.github.com/users/SusieXu",
                "https://api.github.com/users/dangsonbk",
                "https://api.github.com/users/acastrounis",
                "https://api.github.com/users/benedekrozemberczki",
                "https://api.github.com/users/giuliatondin",
                "https://api.github.com/users/jwasham"
            ],
            "contributions": [
                216,
                18,
                13,
                5,
                3,
                3,
                2,
                2,
                2,
                2
            ]
        }
    },
    {
        "stargazers_count": 11090,
        "forks_count": 4297,
        "contributors": {
            "login": [
                "rasbt",
                "erikr",
                "AlexanderKunkel",
                "Naereen",
                "Bachmann1234",
                "MTietze",
                "emptyr1",
                "NeerajSarwan",
                "nipunsadvilkar",
                "sourcesoft"
            ],
            "url": [
                "https://api.github.com/users/rasbt",
                "https://api.github.com/users/erikr",
                "https://api.github.com/users/AlexanderKunkel",
                "https://api.github.com/users/Naereen",
                "https://api.github.com/users/Bachmann1234",
                "https://api.github.com/users/MTietze",
                "https://api.github.com/users/emptyr1",
                "https://api.github.com/users/NeerajSarwan",
                "https://api.github.com/users/nipunsadvilkar",
                "https://api.github.com/users/sourcesoft"
            ],
            "contributions": [
                454,
                2,
                1,
                1,
                1,
                1,
                1,
                1,
                1,
                1
            ]
        }
    },
    {
        "stargazers_count": 3672,
        "forks_count": 1732,
        "contributors": {
            "login": [
                "lawlite19",
                "Alex1996a"
            ],
            "url": [
                "https://api.github.com/users/lawlite19",
                "https://api.github.com/users/Alex1996a"
            ],
            "contributions": [
                119,
                1
            ]
        }
    },
    {
        "stargazers_count": 5898,
        "forks_count": 5153,
        "contributors": {
            "login": [
                "bob7783",
                "lazyprogrammer",
                "superman32432432",
                "nehhen"
            ],
            "url": [
                "https://api.github.com/users/bob7783",
                "https://api.github.com/users/lazyprogrammer",
                "https://api.github.com/users/superman32432432",
                "https://api.github.com/users/nehhen"
            ],
            "contributions": [
                169,
                67,
                29,
                2
            ]
        }
    },
    {
        "stargazers_count": 16971,
        "forks_count": 3093,
        "contributors": {
            "login": [
                "trekhleb",
                "LizhangX"
            ],
            "url": [
                "https://api.github.com/users/trekhleb",
                "https://api.github.com/users/LizhangX"
            ],
            "contributions": [
                243,
                1
            ]
        }
    },
    {
        "stargazers_count": 11070,
        "forks_count": 3354,
        "contributors": {
            "login": [
                "ujjwalkarn",
                "guillaume-chevalier",
                "justmarkham",
                "EtienneT",
                "amitshekhariitbhu",
                "vict0rsch",
                "allthroughthenight",
                "abhshkdz",
                "ThatAndresV",
                "aymericdamien"
            ],
            "url": [
                "https://api.github.com/users/ujjwalkarn",
                "https://api.github.com/users/guillaume-chevalier",
                "https://api.github.com/users/justmarkham",
                "https://api.github.com/users/EtienneT",
                "https://api.github.com/users/amitshekhariitbhu",
                "https://api.github.com/users/vict0rsch",
                "https://api.github.com/users/allthroughthenight",
                "https://api.github.com/users/abhshkdz",
                "https://api.github.com/users/ThatAndresV",
                "https://api.github.com/users/aymericdamien"
            ],
            "contributions": [
                256,
                6,
                5,
                3,
                2,
                2,
                2,
                1,
                1,
                1
            ]
        }
    }
]